fastexchange/__init__.py
fastexchange/converter/__init__.py
fastexchange/converter/base_client.py
fastexchange/converter/clients.py
fastexchange/converter/mappings.py
fastexchange/crypto/__init__.py
fastexchange/crypto/schema.py
fastexchange/crypto/types.py
fastexchange/crypto/usdt.py
fastexchange/currency.py
fastexchange/exceptions.py
fastexchange/foo.py
fastexchange/http.py
fastexchange/utils.py
fastexchange-0.0.1.dist-info/LICENSE
fastexchange-0.0.1.dist-info/METADATA
fastexchange-0.0.1.dist-info/WHEEL
fastexchange-0.0.1.dist-info/RECORD
