Metadata-Version: 2.1
Name: fastexchange
Version: 0.0.1
Summary: d crypto gateway interface ready to use
Home-page: https://github.com/ManiMozaffar/fastexchange
Author: Mani Mozaffar
Author-email: fmani.mozaffar@gmail.com
Requires-Python: >=3.8,<4.0
Classifier: Programming Language :: Python :: 3
Classifier: Programming Language :: Python :: 3.8
Classifier: Programming Language :: Python :: 3.9
Classifier: Programming Language :: Python :: 3.10
Classifier: Programming Language :: Python :: 3.11
Classifier: Programming Language :: Python :: 3.12
Requires-Dist: httpx (>=0.27.0,<0.28.0)
Requires-Dist: lxml (>=5.1.0,<6.0.0)
Requires-Dist: pydantic (>=2.6.4,<3.0.0)
Requires-Dist: pyright (==1.1.350)
Project-URL: Documentation, https://ManiMozaffar.github.io/fastexchange/
Project-URL: Repository, https://github.com/ManiMozaffar/fastexchange
